odoo8_addon_base_business_document_import-8.0.1.2.0-nspkg.pth
odoo_addons/base_business_document_import/README.rst
odoo_addons/base_business_document_import/__init__.py
odoo_addons/base_business_document_import/__openerp__.py
odoo_addons/base_business_document_import/i18n/base_business_document_import.pot
odoo_addons/base_business_document_import/i18n/fr.po
odoo_addons/base_business_document_import/i18n/pt_BR.po
odoo_addons/base_business_document_import/models/__init__.py
odoo_addons/base_business_document_import/models/business_document_import.py
odoo_addons/base_business_document_import/static/description/icon.png
odoo_addons/base_business_document_import/tests/__init__.py
odoo_addons/base_business_document_import/tests/test_business_document_import.py
odoo8_addon_base_business_document_import-8.0.1.2.0.dist-info/METADATA
odoo8_addon_base_business_document_import-8.0.1.2.0.dist-info/WHEEL
odoo8_addon_base_business_document_import-8.0.1.2.0.dist-info/namespace_packages.txt
odoo8_addon_base_business_document_import-8.0.1.2.0.dist-info/top_level.txt
odoo8_addon_base_business_document_import-8.0.1.2.0.dist-info/RECORD
