Metadata-Version: 2.1
Name: odoo8-addon-base-business-document-import
Version: 8.0.1.2.0
Summary: Provides technical tools to import sale orders or supplier invoices
Home-page: http://www.akretion.com
Author: Akretion,Odoo Community Association (OCA)
Author-email: support@odoo-community.org
License: AGPL-3
Platform: UNKNOWN
Classifier: Programming Language :: Python
Classifier: Framework :: Odoo
Classifier: License :: OSI Approved :: GNU Affero General Public License v3
Requires-Python: ~=2.7
Requires-Dist: PyPDF2
Requires-Dist: odoo8-addon-account-tax-unece
Requires-Dist: odoo8-addon-base-vat-sanitized
Requires-Dist: odoo8-addon-product-uom-unece
Requires-Dist: odoo (<9.0a,>=8.0a)
